unearthed/cli/__init__.py
unearthed/cli/auth.py
unearthed/cli/commands/auth.py
unearthed/cli/commands/build.py
unearthed/cli/commands/challenge.py
unearthed/cli/commands/new.py
unearthed/cli/commands/predict.py
unearthed/cli/commands/preprocess.py
unearthed/cli/commands/reset.py
unearthed/cli/commands/score.py
unearthed/cli/commands/submit.py
unearthed/cli/commands/tracker.py
unearthed/cli/commands/train.py
unearthed/cli/config.py
unearthed/cli/docker.py
unearthed/cli/errors.py
unearthed/cli/util.py
unearthed/core/auth/unearthed_auth.py
unearthed/core/auth/unearthed_cognito.py
unearthed/core/models/challenge.py
unearthed/core/models/submission.py
unearthed/logs/__init__.py
unearthed_cli-0.1.9.dist-info/entry_points.txt
unearthed_cli-0.1.9.dist-info/WHEEL
unearthed_cli-0.1.9.dist-info/METADATA
unearthed_cli-0.1.9.dist-info/RECORD
