Metadata-Version: 2.1
Name: unearthed-cli
Version: 0.1.9
Summary: Unearthed CLI Tool
Home-page: https://unearthed.solutions
License: Proprietary
Author: Unearthed Solutions
Author-email: info@unearthed.solutions
Requires-Python: >=3.7,<4.0
Classifier: License :: Other/Proprietary License
Classifier: Programming Language :: Python :: 3
Classifier: Programming Language :: Python :: 3.7
Classifier: Programming Language :: Python :: 3.8
Classifier: Programming Language :: Python :: 3.9
Requires-Dist: PyJWT (>=1.7.1,<2.0.0)
Requires-Dist: boto3 (>=1.16.39,<2.0.0)
Requires-Dist: click (>=7.1.2,<8.0.0)
Requires-Dist: cognitojwt (>=1.2.2,<2.0.0)
Requires-Dist: colorama (>=0.4.4,<0.5.0)
Requires-Dist: docker (>=4.4.0,<5.0.0)
Requires-Dist: outdated (>=0.2.0,<0.3.0)
Requires-Dist: pycognito (>=0.1.4,<0.2.0)
Requires-Dist: requests (>=2.25.1,<3.0.0)
Requires-Dist: tqdm (>=4.54.1,<5.0.0)
Project-URL: Terms and Conditions, https://unearthed.solutions/u/terms
